megaprofiler/__init__.py
megaprofiler/analysis.py
megaprofiler/modeling.py
megaprofiler/outliers.py
megaprofiler/preprocessing.py
megaprofiler/profiling.py
megaprofiler/text_processing.py
megaprofiler/utils.py
megaprofiler/visualization.py
tests/__init__.py
tests/test_analysis.py
tests/test_integration.py
tests/test_profiling.py
megaprofiler-1.0.0.dist-info/LICENSE
megaprofiler-1.0.0.dist-info/METADATA
megaprofiler-1.0.0.dist-info/WHEEL
megaprofiler-1.0.0.dist-info/entry_points.txt
megaprofiler-1.0.0.dist-info/top_level.txt
megaprofiler-1.0.0.dist-info/RECORD
