Metadata-Version: 2.2
Name: megaprofiler
Version: 1.0.0
Summary: megaprofiler is a highly customizable and extensible data profiling library designed to help data scientists and engineers understand their datasets before performing analysis or building models.
Home-page: https://github.com/sidkris/megaprofiler
Author: Siddharth Krishnan
Author-email: sid@sidkrishnan.com
Classifier: Programming Language :: Python :: 3
Classifier: License :: OSI Approved :: MIT License
Classifier: Operating System :: OS Independent
Requires-Python: >=3.6
License-File: LICENSE
Requires-Dist: pandas
Requires-Dist: matplotlib
Requires-Dist: seaborn
Requires-Dist: numpy
Requires-Dist: tabulate
Requires-Dist: scikit-learn
Requires-Dist: imbalanced-learn
Requires-Dist: statsmodels
Requires-Dist: scipy
Dynamic: author
Dynamic: author-email
Dynamic: classifier
Dynamic: description
Dynamic: description-content-type
Dynamic: home-page
Dynamic: requires-dist
Dynamic: requires-python
Dynamic: summary
